Workbook

Sheet BDD_PRODUITS
A1: PRODUIT.ID | B1: DB.LIB | C1: COMPTE.LIB | D1: QTE.2022 | E1: QTE.2023 | F1: QTE.2024 | G1: QTE.Total
A2: 601540 | B2: RAI DEPISTAGE (B50) REF RAID2 | C2: EFS EXAMENS GREFFES HLA ETMALADIES | D2: 35 | E2: 35 | G2: =SUM(BDD_PRODUITS!$D2:$F2) -> 70
A3: 601615 | B3: SUPPLEMENT DIMANCHE (B20) REF 9004 | C3: EFS EXAMENS GREFFES HLA ETMALADIES | E3: 78 | G3: =SUM(BDD_PRODUITS!$D3:$F3) -> 78
A4: 246363 | B4: RAI DEPISTAGE TIA | C4: EFS EXAMENS GREFFES HLA ETMALADIES | E4: 245 | G4: =SUM(BDD_PRODUITS!$D4:$F4) -> 245
A5: 601541 | B5: PHENOTYPE RHESUS KELL (B40) REF RHK | C5: EFS EXAMENS GREFFES HLA ETMALADIES | D5: 66 | E5: 330 | G5: =SUM(BDD_PRODUITS!$D5:$F5) -> 396
A6: 601583 | B6: GROUPE SANGUIN ABO RH(D) (B35) REF ABOD | C6: EFS EXAMENS GREFFES HLA ETMALADIES | D6: 66 | E6: 330 | G6: =SUM(BDD_PRODUITS!$D6:$F6) -> 396
A7: 61651 | B7: DEVIS N°Q2387840 - PHANTOM-TOS | C7: ACCESSOIRES MATERIEL MEDICAL | F7: 1 | G7: =SUM(BDD_PRODUITS!$D7:$F7) -> 1
A8: 61651 | B8: MANDRIN DE JACOB DIAM. 6,35 MM DRILL | C8: ACCESSOIRES MATERIEL MEDICAL | F8: 1 | G8: =SUM(BDD_PRODUITS!$D8:$F8) -> 1
A9: 61651 | B9: Modèle de palpation mammaire + valise de transport | C9: ACCESSOIRES MATERIEL MEDICAL | F9: 1 | G9: =SUM(BDD_PRODUITS!$D9:$F9) -> 1
A10: 61651 | B10: PASSE BROCHES 0,7 A 1.8 MM | C10: ACCESSOIRES MATERIEL MEDICAL | F10: 1 | G10: =SUM(BDD_PRODUITS!$D10:$F10) -> 1
A11: 61651 | B11: POWER SUPPLY 24V | C11: ACCESSOIRES MATERIEL MEDICAL | F11: 1 | G11: =SUM(BDD_PRODUITS!$D11:$F11) -> 1
A12: 61651 | B12: RETINOMAX PRINTER 5 | C12: ACCESSOIRES MATERIEL MEDICAL | F12: 1 | G12: =SUM(BDD_PRODUITS!$D12:$F12) -> 1
A13: 61651 | B13: Tablette IPAD configurée avec l'application logicielle EZYGAIN compatible tapis ema® et réalité | C13: ACCESSOIRES MATERIEL MEDICAL | F13: 1 | G13: =SUM(BDD_PRODUITS!$D13:$F13) -> 1
A14: 222865 | B14: CADRE DE MARCHE DAYS FIXE STANDARD (UNITE) REF 1809460 - SUBSTITUTION OK : REF CO | C14: ACCESSOIRES MATERIEL MEDICAL | D14: 1 | G14: =SUM(BDD_PRODUITS!$D14:$F14) -> 1
A15: 222865 | B15: CADRE DE MARCHE DAYS FIXE STANDARD(UNI TE)REF CONSTR : 091356591 | C15: ACCESSOIRES MATERIEL MEDICAL | E15: 1 | G15: =SUM(BDD_PRODUITS!$D15:$F15) -> 1
A16: 222865 | B16: CADRE DE MARCHE DAYS FIXE - OMEGA (UNITE) Ref Constr : 21010000 SCEMED | C16: ACCESSOIRES MATERIEL MEDICAL | F16: 1 | G16: =SUM(BDD_PRODUITS!$D16:$F16) -> 1
A17: 213594 | B17: MATELAS A EAU 4.5L + ANTI-ALGUE POURBA BYWARMER BW3-020 (UNITE)#24 | C17: ACCESSOIRES MATERIEL MEDICAL | F17: 1 | G17: =SUM(BDD_PRODUITS!$D17:$F17) -> 1
A18: 218420 | B18: DRAP DE TRANSFERT MULTIGLIDE 130X80CM (UNITE) | C18: ACCESSOIRES MATERIEL MEDICAL | D18: 1 | G18: =SUM(BDD_PRODUITS!$D18:$F18) -> 1
A19: 224913 | B19: TENSIOMETRE DE VAQUEZ NANO NOIR ADULTE TAILLE M (UNITE) | C19: ACCESSOIRES MATERIEL MEDICAL | F19: 1 | G19: =SUM(BDD_PRODUITS!$D19:$F19) -> 1
A20: 244061 | B20: TOISE MURALE ADULTE 2M AVEC CURSEUR NYLON ##21 | C20: ACCESSOIRES MATERIEL MEDICAL | E20: 1 | G20: =SUM(BDD_PRODUITS!$D20:$F20) -> 1
A21: 244061 | B21: TOISE MURALE ADULTE 2M AVEC CURSEURNYL ON##23 | C21: ACCESSOIRES MATERIEL MEDICAL | E21: 1 | G21: =SUM(BDD_PRODUITS!$D21:$F21) -> 1
A22: 211100 | B22: COUSSIN UNIVERSEL STANDARD XL 40*60CM REF NEG0381 #24 | C22: ACCESSOIRES MATERIEL MEDICAL | F22: 1 | G22: =SUM(BDD_PRODUITS!$D22:$F22) -> 1
A23: 218181 | B23: BARRE CANOLI DE REDRESSEMENT POUR LITM EDICALISE (DEBARCOUL90)(UNITE) ref 3325735 | C23: ACCESSOIRES MATERIEL MEDICAL | F23: 1 | G23: =SUM(BDD_PRODUITS!$D23:$F23) -> 1
A24: 200013 | B24: DEAMBULATEUR 3 ROUES DRIVE MADRID PANIER & SAC (UNITE) | C24: ACCESSOIRES MATERIEL MEDICAL | F24: 1 | G24: =SUM(BDD_PRODUITS!$D24:$F24) -> 1
A25: 200013 | B25: DEAMBULATEUR 3 ROUES (UNITE) | C25: ACCESSOIRES MATERIEL MEDICAL | E25: 1 | G25: =SUM(BDD_PRODUITS!$D25:$F25) -> 1
A26: 200013 | B26: DEAMBULATEUR 3 ROUES DRIVE MADRID PANIER & SAC (UNITE) | C26: ACCESSOIRES MATERIEL MEDICAL | F26: 1 | G26: =SUM(BDD_PRODUITS!$D26:$F26) -> 1
A27: 211111 | B27: ROLLATOR 2 ROUES BLEU (UNITE) | C27: ACCESSOIRES MATERIEL MEDICAL | E27: 1 | G27: =SUM(BDD_PRODUITS!$D27:$F27) -> 1
A28: 211111 | B28: ROLLATOR 2 ROUES BLEU (UNITE) REF CONSTR 91558006 | C28: ACCESSOIRES MATERIEL MEDICAL | D28: 1 | G28: =SUM(BDD_PRODUITS!$D28:$F28) -> 1
A29: 213472 | B29: DIAPASON HARTMANN SANS CURSEUR 512VD (UNITE)#23 REF DIA512 | C29: ACCESSOIRES MATERIEL MEDICAL | E29: 1 | G29: =SUM(BDD_PRODUITS!$D29:$F29) -> 1
A30: 213472 | B30: DIAPASON HARTMANN SANS CURSEUR 512VD(U NITE)REF DIA512 | C30: ACCESSOIRES MATERIEL MEDICAL | D30: 1 | G30: =SUM(BDD_PRODUITS!$D30:$F30) -> 1
A31: 213483 | B31: PELVIC-TILT REGLABLE (10 UNITES) #24 | C31: ACCESSOIRES MATERIEL MEDICAL | F31: 1 | G31: =SUM(BDD_PRODUITS!$D31:$F31) -> 1
A32: 218459 | B32: FEMUR GAUCHE (UNITE) REF 1019360 | C32: ACCESSOIRES MATERIEL MEDICAL | E32: 1 | G32: =SUM(BDD_PRODUITS!$D32:$F32) -> 1
A33: 218778 | B33: LUNETTES PRISMATIQUES VE223 (PAIRE)REF VE223 | C33: ACCESSOIRES MATERIEL MEDICAL | E33: 1 | G33: =SUM(BDD_PRODUITS!$D33:$F33) -> 1
A34: 231532 | B34: PÈSE PERSONNE SECA_878_DR (UNITE) REF CONSTR 8787041119 REF FOURN 3299906 | C34: ACCESSOIRES MATERIEL MEDICAL | E34: 1 | G34: =SUM(BDD_PRODUITS!$D34:$F34) -> 1
A35: 244870 | B35: SET DE CONNEXION EN SILICONE, POUR COLOSCOPES, GASTROSCOPES ET | C35: ACCESSOIRES MATERIEL MEDICAL | E35: 1 | G35: =SUM(BDD_PRODUITS!$D35:$F35) -> 1
A36: 244870 | B36: SET DE CONNEXION EN SILICONE, POURCOLO SCOPES, GASTROSCOPES ETDUODENESCOPES S | C36: ACCESSOIRES MATERIEL MEDICAL | E36: 1 | G36: =SUM(BDD_PRODUITS!$D36:$F36) -> 1
A37: 245669 | B37: HUGO-ADAPTATEUR ENDOSCOPE(UNITE) | C37: ACCESSOIRES MATERIEL MEDICAL | E37: 1 | G37: =SUM(BDD_PRODUITS!$D37:$F37) -> 1
A38: 213599 | B38: PLANCHE DE TRANSFERT BANANA 68*21CM(UN ITE)#23REF SIECA622000 | C38: ACCESSOIRES MATERIEL MEDICAL | E38: 1 | G38: =SUM(BDD_PRODUITS!$D38:$F38) -> 1
A39: 215211 | B39: MONITEUR O2 ENVITEC MY SIGN O (UNITE) | C39: ACCESSOIRES MATERIEL MEDICAL | F39: 1 | G39: =SUM(BDD_PRODUITS!$D39:$F39) -> 1
A40: 218175 | B40: TROUSSE DE SECOURS MULTISAN 12-25PERSO NNES VIDE (UNITE)REF MULTISANV | C40: ACCESSOIRES MATERIEL MEDICAL | F40: 1 | G40: =SUM(BDD_PRODUITS!$D40:$F40) -> 1
A41: 218185 | B41: SAC A DOS URGENCE TONIC BLEU NUIT(UNIT E)REF SEC1092 | C41: ACCESSOIRES MATERIEL MEDICAL | D41: 1 | G41: =SUM(BDD_PRODUITS!$D41:$F41) -> 1
A42: 218211 | B42: DIAPASON DE RYDEL SEIFER (UNITE) REF PEO125 | C42: ACCESSOIRES MATERIEL MEDICAL | E42: 1 | G42: =SUM(BDD_PRODUITS!$D42:$F42) -> 1
A43: 218932 | B43: AMPOULIER - CAPACITE 15 AMPOULES(UNITE )REF FAB OPT1116 | C43: ACCESSOIRES MATERIEL MEDICAL | F43: 1 | G43: =SUM(BDD_PRODUITS!$D43:$F43) -> 1
A44: 229420 | B44: COUPE-CEINTURE DE SECURITE REF 2551 | C44: ACCESSOIRES MATERIEL MEDICAL | E44: 1 | G44: =SUM(BDD_PRODUITS!$D44:$F44) -> 1
A45: 229425 | B45: COUVERTURE DE SURVIE PEDIATRIQUE 110*140 (UNITE) REF CONSTR. 4700FCE-ENFANT | C45: ACCESSOIRES MATERIEL MEDICAL | F45: 1 | G45: =SUM(BDD_PRODUITS!$D45:$F45) -> 1
A46: 231526 | B46: POMPE NUTRITION AMIKA FR REF Z044110 | C46: ACCESSOIRES MATERIEL MEDICAL | E46: 1 | G46: =SUM(BDD_PRODUITS!$D46:$F46) -> 1
A47: 242353 | B47: DERMATOSCOPE MINI 3000 LED TETE + POIGNEE + EMBOUT SANS GRAD. + HUILE | C47: ACCESSOIRES MATERIEL MEDICAL | E47: 1 | G47: =SUM(BDD_PRODUITS!$D47:$F47) -> 1
A48: 242353 | B48: DERMATOSCOPE MINI 3000 LED TETE +POIGN EE + EMBOUT SANS GRAD. + HUILE | C48: ACCESSOIRES MATERIEL MEDICAL | E48: 1 | G48: =SUM(BDD_PRODUITS!$D48:$F48) -> 1
A49: 242548 | B49: CONNECTIQUE SILICONE POUR ECHOENDOCOPES PENTAX SERIES 70K ET J10 | C49: ACCESSOIRES MATERIEL MEDICAL | F49: 1 | G49: =SUM(BDD_PRODUITS!$D49:$F49) -> 1
A50: 244869 | B50: SET DE CONNEXION DE STOCKAGE, POURL'IN JECTION DE PLASMA STSC-1040(GRATUIT SU R MARCHE) | C50: ACCESSOIRES MATERIEL MEDICAL | D50: 1 | G50: =SUM(BDD_PRODUITS!$D50:$F50) -> 1
A51: 245405 | B51: PLANCHE DE TRANSFERT AMAGNETIQUE ROLLBODY RIGIDE MINI 90*50CM REF CONSTR ROLBODY1010 | C51: ACCESSOIRES MATERIEL MEDICAL | F51: 1 | G51: =SUM(BDD_PRODUITS!$D51:$F51) -> 1
A52: 245405 | B52: PLANCHE DE TRANSFERT AMAGNETIQUEROLLBO DY RIGIDE MINI 90*50CMREF CONSTR ROLBO DY1010 | C52: ACCESSOIRES MATERIEL MEDICAL | E52: 1 | G52: =SUM(BDD_PRODUITS!$D52:$F52) -> 1
A53: 246656 | B53: ROBINET RTM3 COMPLET O²REF FABRICANT 1 6954)#23 | C53: ACCESSOIRES MATERIEL MEDICAL | F53: 1 | G53: =SUM(BDD_PRODUITS!$D53:$F53) -> 1
A54: 246742 | B54: LAMPE LOUPE LED LUXO LFM LED G25DIOPTR IE 127MM (UNITE)REF CONSTR LFG028261 | C54: ACCESSOIRES MATERIEL MEDICAL | E54: 1 | G54: =SUM(BDD_PRODUITS!$D54:$F54) -> 1
A55: 247719 | B55: DEAMBULATEUR 2 ROUES PLIANT(UNITE)REF DEAM243 | C55: ACCESSOIRES MATERIEL MEDICAL | F55: 1 | G55: =SUM(BDD_PRODUITS!$D55:$F55) -> 1
A56: 249121 | B56: CISEAUX DE POTTS(UNITE) WEB_233551788-283538 | C56: ACCESSOIRES MATERIEL MEDICAL | F56: 1 | G56: =SUM(BDD_PRODUITS!$D56:$F56) -> 1
A57: 213470 | B57: TOISE POUR BEBES AVEC CURSEUR EXTRA LARGE DE 0 A 99CM (UNITE) REF CONSTR 2071714008 | C57: ACCESSOIRES MATERIEL MEDICAL | E57: 1 | G57: =SUM(BDD_PRODUITS!$D57:$F57) -> 1
A58: 213882 | B58: BRASSARD ENFANT OMRON (UNITE)REF 23080 4 | C58: ACCESSOIRES MATERIEL MEDICAL | D58: 1 | G58: =SUM(BDD_PRODUITS!$D58:$F58) -> 1
A59: 214720 | B59: TONOMETRE DE SCHIOTZ C , ECHELLE INCLINEE (UNITE) REF KL4445 | C59: ACCESSOIRES MATERIEL MEDICAL | D59: 1 | G59: =SUM(BDD_PRODUITS!$D59:$F59) -> 1
A60: 218474 | B60: PIECE EN SILICONE VO2 POUR ADULTE (UNITE) REF 2044243-028 | C60: ACCESSOIRES MATERIEL MEDICAL | E60: 1 | G60: =SUM(BDD_PRODUITS!$D60:$F60) -> 1
A61: 218492 | B61: ROULEAUX DE FEUILLES DE PROTECTIONBOUC HE A BOUCHE (6 UNITES)REF 486ZJ | C61: ACCESSOIRES MATERIEL MEDICAL | E61: 1 | G61: =SUM(BDD_PRODUITS!$D61:$F61) -> 1
A62: 218517 | B62: KIT OXYMETRE POUR TETIERE MICROMEDSD L TM 64 (UNITE)REF KIT OXY BSP | C62: ACCESSOIRES MATERIEL MEDICAL | E62: 1 | G62: =SUM(BDD_PRODUITS!$D62:$F62) -> 1
A63: 218594 | B63: ELECTRODES BCM ( 40 UNITES) REF M351431 | C63: ACCESSOIRES MATERIEL MEDICAL | F63: 1 | G63: =SUM(BDD_PRODUITS!$D63:$F63) -> 1
A64: 218719 | B64: PLANCHE SPLIT RIGIDE 76X22CM (SIIM403)(UNITE) REF 3298643 | C64: ACCESSOIRES MATERIEL MEDICAL | F64: 1 | G64: =SUM(BDD_PRODUITS!$D64:$F64) -> 1
A65: 218765 | B65: PODOSCOPE PODO'LINEELLA 150KG REF P4 ( UNITE)REF 061020 | C65: ACCESSOIRES MATERIEL MEDICAL | D65: 1 | G65: =SUM(BDD_PRODUITS!$D65:$F65) -> 1
A66: 218861 | B66: ROLLATOR CLASSIC 4 ROUES BLEU (UNITE) REF CONSTR 091555101 | C66: ACCESSOIRES MATERIEL MEDICAL | D66: 1 | G66: =SUM(BDD_PRODUITS!$D66:$F66) -> 1
A67: 218883 | B67: KIT PIECES DETACHEES STETHO LITTMANN CLASSIC II S.E SELECT NOIR (10 UNITES) REF 40005 | C67: ACCESSOIRES MATERIEL MEDICAL | F67: 1 | G67: =SUM(BDD_PRODUITS!$D67:$F67) -> 1
A68: 225611 | B68: DEAMBULATEUR 3 ROUES DAYS - COLORISQUA RTZ AVEC PANIER, PLATEAU ET SACREF CON STR 091169978 | C68: ACCESSOIRES MATERIEL MEDICAL | D68: 1 | G68: =SUM(BDD_PRODUITS!$D68:$F68) -> 1
A69: 240327 | B69: CAPTEUR D EFFORT POUR SANGLES PRIPOLYS OMNO SOMNOSCREEN | C69: ACCESSOIRES MATERIEL MEDICAL | E69: 1 | G69: =SUM(BDD_PRODUITS!$D69:$F69) -> 1
A70: 242723 | B70: PANIER CLOISONNE EN FIL INOX, 250ML, 24 BIBERONS SANS ANSES PRET - GRATUITE - | C70: ACCESSOIRES MATERIEL MEDICAL | D70: 1 | G70: =SUM(BDD_PRODUITS!$D70:$F70) -> 1
A71: 243382 | B71: PLOT DE POSITIONNEMENT COMPOSITE PERFO MANCE PLUS 40X12X8.5CM (UNITE) | C71: ACCESSOIRES MATERIEL MEDICAL | E71: 1 | G71: =SUM(BDD_PRODUITS!$D71:$F71) -> 1
A72: 245677 | B72: MASQUE, PETIT, POUR RHINO 31,RHINO 300 (TAILLE 3-4) (UNITE) | C72: ACCESSOIRES MATERIEL MEDICAL | D72: 1 | G72: =SUM(BDD_PRODUITS!$D72:$F72) -> 1
A73: 246667 | B73: COUSSIN VISCO LOMBAIRE STANDARD (UNITE) | C73: ACCESSOIRES MATERIEL MEDICAL | D73: 1 | G73: =SUM(BDD_PRODUITS!$D73:$F73) -> 1
A74: 247446 | B74: GRIFFE FORMAGE 6X8 BECS ARRONDIS(UNITE ) | C74: ACCESSOIRES MATERIEL MEDICAL | E74: 1 | G74: =SUM(BDD_PRODUITS!$D74:$F74) -> 1
A75: 247518 | B75: MASQUE, GRAND, POUR RHINO 31,RHINO 300 (TAILLE 4-5) (UNITE) | C75: ACCESSOIRES MATERIEL MEDICAL | E75: 1 | G75: =SUM(BDD_PRODUITS!$D75:$F75) -> 1
A76: 247565 | B76: SCANLAN® LEGACY MICRO PORTE-AIGUILLEPO IGNÉE RONDE (UNITE) | C76: ACCESSOIRES MATERIEL MEDICAL | E76: 1 | G76: =SUM(BDD_PRODUITS!$D76:$F76) -> 1
A77: 247648 | B77: CALIBRATION BODY ELECTROMAGNETICUNITE | C77: ACCESSOIRES MATERIEL MEDICAL | E77: 1 | G77: =SUM(BDD_PRODUITS!$D77:$F77) -> 1
A78: 247797 | B78: LAMPE LOUPE GROSSISSEMENT 1,75 X ET 4 X Ø 85 MM (UNITE) REF CONTR 7706VE-MOINEAU | C78: ACCESSOIRES MATERIEL MEDICAL | E78: 1 | G78: =SUM(BDD_PRODUITS!$D78:$F78) -> 1
A79: 250546 | B79: VESTE D ENTRAINEMENT HEIMLICH ADULTE (UNITE) | C79: ACCESSOIRES MATERIEL MEDICAL | F79: 1 | G79: =SUM(BDD_PRODUITS!$D79:$F79) -> 1
A80: 250564 | B80: SOULEVE JAMBES | C80: ACCESSOIRES MATERIEL MEDICAL | F80: 1 | G80: =SUM(BDD_PRODUITS!$D80:$F80) -> 1
A81: 222865 | B81: CADRE DE MARCHE DAYS FIXE STANDARD(UNI TE)REF 1809460 | C81: ACCESSOIRES MATERIEL MEDICAL | D81: 2 | E81: 0 | G81: =SUM(BDD_PRODUITS!$D81:$F81) -> 2
A82: 213594 | B82: MATELAS A EAU 4.5L + ANTI-ALGUE POUR BABYWARMER BW3-020 (UNITE) #22 | C82: ACCESSOIRES MATERIEL MEDICAL | D82: 2 | G82: =SUM(BDD_PRODUITS!$D82:$F82) -> 2
A83: 213594 | B83: MATELAS A EAU 4.5L + ANTI-ALGUE POURBA BYWARMER BW3-020 (UNITE)REF BW-50-003 | C83: ACCESSOIRES MATERIEL MEDICAL | D83: 2 | G83: =SUM(BDD_PRODUITS!$D83:$F83) -> 2
A84: 228883 | B84: JEU DE 3 FILS CEI USI A PINCE 0,7M(M16 72A) (UNITE)REF 2410867 | C84: ACCESSOIRES MATERIEL MEDICAL | D84: 2 | G84: =SUM(BDD_PRODUITS!$D84:$F84) -> 2
A85: 218420 | B85: DRAP DE TRANSFERT MULTIGLIDE 130X80CM( UNITE)REF CONSTR SIIM130 - SUBSTITUTION OK EN 130*90CM REF32986 | C85: ACCESSOIRES MATERIEL MEDICAL | E85: 2 | G85: =SUM(BDD_PRODUITS!$D85:$F85) -> 2
A86: 224913 | B86: TENSIOMETRE DE VAQUEZ NANO TAILLE M NOIRADULTE (UNITE) | C86: ACCESSOIRES MATERIEL MEDICAL | F86: 2 | G86: =SUM(BDD_PRODUITS!$D86:$F86) -> 2
A87: 240216 | B87: CS9600, SUPPORT MENTONNIER | C87: ACCESSOIRES MATERIEL MEDICAL | D87: 2 | G87: =SUM(BDD_PRODUITS!$D87:$F87) -> 2
A88: 240216 | B88: SUPPORT MENTON PANORAMIQUE CS9600 | C88: ACCESSOIRES MATERIEL MEDICAL | D88: 2 | G88: =SUM(BDD_PRODUITS!$D88:$F88) -> 2
A89: 213456 | B89: GONIOMETRE BALTHAZARD PLASTIQUE(UNITE) REF GONIO24 | C89: ACCESSOIRES MATERIEL MEDICAL | D89: 2 | G89: =SUM(BDD_PRODUITS!$D89:$F89) -> 2
A90: 213458 | B90: OXYMETRE DE POULS AFFICHAGE DIRECT SUR DOIGT SPO2 PULSATIONS (UNITE)REF CONST | C90: ACCESSOIRES MATERIEL MEDICAL | E90: 2 | G90: =SUM(BDD_PRODUITS!$D90:$F90) -> 2
A91: 218181 | B91: BARRE CANOLI DE REDRESSEMENT POUR LIT MEDICALISE (DEBARCOUL90)(UNITE) | C91: ACCESSOIRES MATERIEL MEDICAL | F91: 2 | G91: =SUM(BDD_PRODUITS!$D91:$F91) -> 2
A92: 66639 | B92: CAPTEUR SPO2 ALL FIT PEDIATRIQUE USAGE USAGE UNIQUE (10 UNITES) REF FAB TSAF10 5 (GE) | C92: ACCESSOIRES MATERIEL MEDICAL | F92: 2 | G92: =SUM(BDD_PRODUITS!$D92:$F92) -> 2
A93: 218154 | B93: RELEVEUR DE PIED MODELE SUEDOIS TAILLE MOYENNE GAUCHE (UNITE) REF RPS11 | C93: ACCESSOIRES MATERIEL MEDICAL | E93: 2 | G93: =SUM(BDD_PRODUITS!$D93:$F93) -> 2
A94: 218156 | B94: RELEVEUR DE PIED MODELE SUEDOIS GRANDE TAILLE GAUCHE (UNITE) REF RPS21 | C94: ACCESSOIRES MATERIEL MEDICAL | E94: 2 | G94: =SUM(BDD_PRODUITS!$D94:$F94) -> 2
A95: 218156 | B95: RELEVEUR DE PIED MODELE SUEDOIS GRANDE TAILLE GAUCHE (UNITE) REF RPS21 #24 | C95: ACCESSOIRES MATERIEL MEDICAL | F95: 2 | G95: =SUM(BDD_PRODUITS!$D95:$F95) -> 2
A96: 218156 | B96: RELEVEUR DE PIED MODELE SUEDOISGRANDE TAILLE GAUCHE (UNITE)REF RPS21 | C96: ACCESSOIRES MATERIEL MEDICAL | E96: 2 | G96: =SUM(BDD_PRODUITS!$D96:$F96) -> 2
A97: 218493 | B97: PANSEMENT COMPRESSIF ISRAELIEN (UNITE) REF 304250 | C97: ACCESSOIRES MATERIEL MEDICAL | E97: 2 | G97: =SUM(BDD_PRODUITS!$D97:$F97) -> 2
A98: 231532 | B98: PÈSE PERSONNE SECA_878_DR (UNITE) REF CONSTR 8787041119 | C98: ACCESSOIRES MATERIEL MEDICAL | E98: 2 | G98: =SUM(BDD_PRODUITS!$D98:$F98) -> 2
A99: 240215 | B99: K9000, SUPPORT MENTONNIER PANORAMIQUE | C99: ACCESSOIRES MATERIEL MEDICAL | D99: 2 | G99: =SUM(BDD_PRODUITS!$D99:$F99) -> 2
A100: 240215 | B100: SUPPORT MENTON PANORAMIQUE CS9300 | C100: ACCESSOIRES MATERIEL MEDICAL | D100: 2 | G100: =SUM(BDD_PRODUITS!$D100:$F100) -> 2
...

Sheet dictionnaire
A1: PRODUIT.ID | B1: identifiant du produit
A2: DB.LIB | B2: Libellé du produit, quantité et unité
A3: COMPTE.LIB | B3: libellé du compte associé
A4: QTE.2022 | B4: Quantité 2022
A5: QTE.2023 | B5: Quantité 2023
A6: QTE.2024 | B6: Quantité 2024
A7: QTE.total | B7: Quantité total entre 2022 et 2024
